{
  "project_info": {
    "project_number": "256084022437",
    "firebase_url": "https://alert-cliente.firebaseio.com",
    "project_id": "alert-cliente",
    "storage_bucket": "alert-cliente.appspot.com"
  },
  "client": [
    {
      "client_info": {
        "mobilesdk_app_id": "1:256084022437:android:20c4dfe8aff4384b",
        "android_client_info": {
          "package_name": "com.alerta.cliente"
        }
      },
      "oauth_client": [
        {
          "client_id": "256084022437-c3qq1tpnqb89sm7fkdrmahjptufbhvh0.apps.googleusercontent.com",
          "client_type": 1,
          "android_info": {
            "package_name": "com.alerta.cliente",
            "certificate_hash": "d41a82e47e6ea6ca02e7b44ec4384cb3f2c808fa"
          }
        },
        {
          "client_id": "256084022437-hv520tl2f3aepdv4jc5tl8r2cadp7p2a.apps.googleusercontent.com",
          "client_type": 3
        }
      ],
      "api_key": [
        {
          "current_key": "AIzaSyAtnoC9V9oQrBz7VQIA1-C2tau-YmT91Bk"
        }
      ],
      "services": {
        "analytics_service": {
          "status": 1
        },
        "appinvite_service": {
          "status": 2,
          "other_platform_oauth_client": [
            {
              "client_id": "256084022437-hv520tl2f3aepdv4jc5tl8r2cadp7p2a.apps.googleusercontent.com",
              "client_type": 3
            },
            {
              "client_id": "256084022437-ovub506mo03pl3a0iem0ubcfgj4u0qcc.apps.googleusercontent.com",
              "client_type": 2,
              "ios_info": {
                "bundle_id": "com.alerta.cliente"
              }
            }
          ]
        },
        "ads_service": {
          "status": 2
        }
      }
    }
  ],
  "configuration_version": "1"
}